qlib/__init__.py
qlib_tool-0.1.dist-info/METADATA
qlib_tool-0.1.dist-info/WHEEL
qlib_tool-0.1.dist-info/top_level.txt
qlib_tool-0.1.dist-info/RECORD
