Metadata-Version: 2.1
Name: qlib-tool
Version: 0.1
Summary: QLib For OiL n Gas
Home-page: https://github.com/Q-Engineering/qlib
Author: qengineering
Author-email: david@q.engineering
License: MIT
Platform: UNKNOWN
